[
   {
      "text" : "A U.S. Navy F5L seaplane took off from Hampton Roads, Virginia, using a radio compass for the first time. The pilots located and flew to the Battleship Ohio about 94 miles offshore.",
      "links" : [
         "http://www.history.navy.mil/branches/avchr3.htm"
      ],
      "year" : "1920"
   },
   {
      "text" : "The AK-47 went into production in the Soviet Union -- the name stands for Automatic rifle Kalashnikov model of 1947.",
      "links" : [
         "http://www.wired.com/thisdayintech/2009/07/dayintech_0706/"
      ],
      "year" : "1947"
   },
   {
      "text" : "AOL settled lawsuits in California that accused the company of misleading subscribers about monthly service charges.",
      "links" : [
         "http://news.cnet.com/AOL-to-settle-class-action-suits/2100-1023_3-216681.html"
      ],
      "year" : "1996"
   }
]
