[
   {
      "text" : "The U.S. Patent Office approved Thomas Davenport's application for a patent on an \"Improvement in Propelling Machinery by Magnetism and Electro-Magnetism.\" We'd call it an electric motor.",
      "links" : [
         "http://www.google.com/patents?id=NM0-AAAAEBAJ&printsec=abstract&zoom=4#v=onepage&q&f=false"
      ],
      "year" : "1837"
   },
   {
      "text" : "Charles Jenkins Laboratories of Washington, D.C. became the first holder of a television license from the Federal Radio Commission.",
      "links" : [
         "http://www.nrcdxas.org/articles/1stfacts.txt"
      ],
      "year" : "1928"
   },
   {
      "text" : "A US patent for a photographing apparatus was issued to George Lewis McCarthy, who called it a Checkograph. It was the first bank check photographing device.",
      "links" : [
         "http://www.google.com/patents?id=6q9VAAAAEBAJ&printsec=abstract&zoom=4#v=onepage&q&f=false"
      ],
      "year" : "1930"
   }
]
